 [
  {"medicinecode":"4123456","medicinename":"Abemaciclib","pack_quantity":50,"pack_unit":"pcs"},
  {"medicinecode":"4123323","medicinename":"Abilify","pack_quantity":100,"pack_unit":"pcs"},
  {"medicinecode":"4123509","medicinename":"Abstral","pack_quantity":200,"pack_unit":"pcs"},
  {"medicinecode":"4123510","medicinename":"ACCod","pack_quantity":50,"pack_unit":"pcs"},
  {"medicinecode":"4123324","medicinename":"Acemap","pack_quantity":1000,"pack_unit":"mg"},
  {"medicinecode":"4123146","medicinename":"Acetazolamide","pack_quantity":200,"pack_unit":"pcs"},
  {"medicinecode":"4123562","medicinename":"Acnecare","pack_quantity":50,"pack_unit":"pcs"},
  {"medicinecode":"4123248","medicinename":"Acrivastine t/m 24 pcs","pack_quantity":100,"pack_unit":"pcs"},
  {"medicinecode":"4123511","medicinename":"Actiq","pack_quantity":200,"pack_unit":"pcs"},
  {"medicinecode":"4123635","medicinename":"Adartrel","pack_quantity":50,"pack_unit":"pcs"},
  {"medicinecode":"4123249","medicinename":"Aerius","pack_quantity":100,"pack_unit":"pcs"},
  {"medicinecode":"4123457","medicinename":"Afatinib","pack_quantity":200,"pack_unit":"pcs"},
  {"medicinecode":"4123195","medicinename":"Agomelatine","pack_quantity":5000,"pack_unit":"mg"},
  {"medicinecode":"4123636","medicinename":"Akineton","pack_quantity":100,"pack_unit":"pcs"},
  {"medicinecode":"4123325","medicinename":"Aktiprol","pack_quantity":200,"pack_unit":"pcs"},
  {"medicinecode":"4123458","medicinename":"Alecensa","pack_quantity":50,"pack_unit":"pcs"},
  {"medicinecode":"4123459","medicinename":"Alectinib","pack_quantity":100,"pack_unit":"pcs"},
  {"medicinecode":"4123512","medicinename":"Alfentanil","pack_quantity":200,"pack_unit":"pcs"},
  {"medicinecode":"4123250","medicinename":"Alimemazine","pack_quantity":50,"pack_unit":"pcs"},
  {"medicinecode":"4123251","medicinename":"Allegra fexotabs","pack_quantity":100,"pack_unit":"pcs"},
  {"medicinecode":"4123252","medicinename":"Allerfre","pack_quantity":200,"pack_unit":"pcs"},
  {"medicinecode":"4123253","medicinename":"Allergietablet Cetirizine","pack_quantity":50,"pack_unit":"pcs"},
  {"medicinecode":"4123424","medicinename":"Almogran","pack_quantity":1000,"pack_unit":"mg"},
  {"medicinecode":"4123425","medicinename":"Almotriptan","pack_quantity":200,"pack_unit":"pcs"},
  {"medicinecode":"4123460","medicinename":"Alpelisib","pack_quantity":50,"pack_unit":"pcs"},
  {"medicinecode":"4123370","medicinename":"Alprazolam","pack_quantity":100,"pack_unit":"pcs"},
  {"medicinecode":"4123254","medicinename":"Altriabak","pack_quantity":200,"pack_unit":"pcs"},
  {"medicinecode":"4123637","medicinename":"Amantadine","pack_quantity":50,"pack_unit":"pcs"},
  {"medicinecode":"4123123","medicinename":"Amfexa","pack_quantity":100,"pack_unit":"pcs"},
  {"medicinecode":"4123563","medicinename":"Amfotericine B","pack_quantity":200,"pack_unit":"pcs"},
  {"medicinecode":"4123326","medicinename":"amisulpride","pack_quantity":50,"pack_unit":"pcs"},
  {"medicinecode":"4123196","medicinename":"Amitriptyline","pack_quantity":100,"pack_unit":"pcs"},
  {"medicinecode":"4123681","medicinename":"Ancotil","pack_quantity":200,"pack_unit":"pcs"},
  {"medicinecode":"4123682","medicinename":"Anidulafungine","pack_quantity":50,"pack_unit":"pcs"},
  {"medicinecode":"4123496","medicinename":"Antabus","pack_quantity":100,"pack_unit":"pcs"},
  {"medicinecode":"4123680","medicinename":"Antischimmel","pack_quantity":200,"pack_unit":"pcs"},
  {"medicinecode":"4123638","medicinename":"APO","pack_quantity":50,"pack_unit":"pcs"},
  {"medicinecode":"4123639","medicinename":"Apomorfine","pack_quantity":100,"pack_unit":"pcs"},
  {"medicinecode":"4123564","medicinename":"Arava","pack_quantity":200,"pack_unit":"pcs"},
  {"medicinecode":"4123327","medicinename":"Aripiprazol","pack_quantity":50,"pack_unit":"pcs"},
  {"medicinecode":"4123640","medicinename":"Artane","pack_quantity":100,"pack_unit":"pcs"},
  {"medicinecode":"4123565","medicinename":"Aspendos","pack_quantity":200,"pack_unit":"pcs"},
  {"medicinecode":"4123124","medicinename":"Atomoxetine","pack_quantity":50,"pack_unit":"pcs"},
  {"medicinecode":"4123125","medicinename":"Audalis","pack_quantity":100,"pack_unit":"pcs"},
  {"medicinecode":"4123197","medicinename":"Aurorix","pack_quantity":200,"pack_unit":"pcs"},
  {"medicinecode":"4123461","medicinename":"Axitinib","pack_quantity":50,"pack_unit":"pcs"},
  {"medicinecode":"4123641","medicinename":"Azilect","pack_quantity":100,"pack_unit":"pcs"},
  {"medicinecode":"4123497","medicinename":"Baclofen","pack_quantity":200,"pack_unit":"pcs"},
  {"medicinecode":"4123566","medicinename":"Biltricide","pack_quantity":50,"pack_unit":"pcs"},
  {"medicinecode":"4123462","medicinename":"Binimetinib","pack_quantity":100,"pack_unit":"pcs"},
  {"medicinecode":"4123642","medicinename":"Biperideen","pack_quantity":200,"pack_unit":"pcs"},
  {"medicinecode":"4123415","medicinename":"Bisolnex","pack_quantity":50,"pack_unit":"pcs"},
  {"medicinecode":"4123463","medicinename":"Bortezomib","pack_quantity":100,"pack_unit":"pcs"},
  {"medicinecode":"4123464","medicinename":"Bosulif","pack_quantity":200,"pack_unit":"pcs"},
  {"medicinecode":"4123465","medicinename":"Bosutinib","pack_quantity":50,"pack_unit":"pcs"},
  {"medicinecode":"4123328","medicinename":"brexpiprazol","pack_quantity":100,"pack_unit":"pcs"},
  {"medicinecode":"4123198","medicinename":"Brintellix","pack_quantity":200,"pack_unit":"pcs"},
  {"medicinecode":"4123147","medicinename":"Brivaracetam","pack_quantity":50,"pack_unit":"pcs"},
  {"medicinecode":"4123148","medicinename":"Briviact","pack_quantity":100,"pack_unit":"pcs"},
  {"medicinecode":"4123371","medicinename":"Bromazepam","pack_quantity":200,"pack_unit":"pcs"},
  {"medicinecode":"4123372","medicinename":"Bromazepamum","pack_quantity":50,"pack_unit":"pcs"},
  {"medicinecode":"4123643","medicinename":"Bromocriptine","pack_quantity":100,"pack_unit":"pcs"},
  {"medicinecode":"4123513","medicinename":"Bronchicum extra sterk stroop","pack_quantity":200,"pack_unit":"pcs"},
  {"medicinecode":"4123329","medicinename":"Broomperidol","pack_quantity":50,"pack_unit":"pcs"},
  {"medicinecode":"4123373","medicinename":"Brotizolam","pack_quantity":100,"pack_unit":"pcs"},
  {"medicinecode":"4123514","medicinename":"Bunalict","pack_quantity":2000,"pack_unit":"mg"},
  {"medicinecode":"4123515","medicinename":"Buprenorfine","pack_quantity":50,"pack_unit":"pcs"},
  {"medicinecode":"4123498","medicinename":"Bupropion","pack_quantity":100,"pack_unit":"pcs"},
  {"medicinecode":"4123374","medicinename":"Buspiron","pack_quantity":200,"pack_unit":"pcs"},
  {"medicinecode":"4123516","medicinename":"BuTrans","pack_quantity":50,"pack_unit":"pcs"},
  {"medicinecode":"4123330","medicinename":"Byannli","pack_quantity":100,"pack_unit":"pcs"},
  {"medicinecode":"4123375","medicinename":"Byfavo","pack_quantity":200,"pack_unit":"pcs"},
  {"medicinecode":"4123567","medicinename":"Cabergoline","pack_quantity":50,"pack_unit":"pcs"},
  {"medicinecode":"4123466","medicinename":"Cabometyx","pack_quantity":100,"pack_unit":"pcs"},
  {"medicinecode":"4123467","medicinename":"Cabozantinib","pack_quantity":200,"pack_unit":"pcs"},
  {"medicinecode":"4123199","medicinename":"Camcolit","pack_quantity":50,"pack_unit":"pcs"},
  {"medicinecode":"4123683","medicinename":"Cancidas","pack_quantity":100,"pack_unit":"pcs"},
  {"medicinecode":"4123568","medicinename":"Cannabis","pack_quantity":200,"pack_unit":"pcs"},
  {"medicinecode":"4123569","medicinename":"Cannabis flos Bedica granulaat","pack_quantity":50,"pack_unit":"pcs"},
  {"medicinecode":"4123570","medicinename":"Cannabis flos Bediol granulaat","pack_quantity":100,"pack_unit":"pcs"},
  {"medicinecode":"4123571","medicinename":"Cannabis flos Bedrobinol","pack_quantity":200,"pack_unit":"pcs"},
  {"medicinecode":"4123572","medicinename":"Cannabis flos Bedrocan","pack_quantity":50,"pack_unit":"pcs"},
  {"medicinecode":"4123149","medicinename":"Carbamazepine","pack_quantity":100,"pack_unit":"pcs"},
  {"medicinecode":"4123468","medicinename":"Carfilzomib","pack_quantity":200,"pack_unit":"pcs"},
  {"medicinecode":"4123331","medicinename":"Cariprazine","pack_quantity":50,"pack_unit":"pcs"},
  {"medicinecode":"4123684","medicinename":"Caspofungine","pack_quantity":100,"pack_unit":"pcs"},
  {"medicinecode":"4123307","medicinename":"Catapresan","pack_quantity":200,"pack_unit":"pcs"},
  {"medicinecode":"4123255","medicinename":"Cetirizine","pack_quantity":50,"pack_unit":"pcs"},
  {"medicinecode":"4123256","medicinename":"Cetirizine t/m 10 pcs","pack_quantity":100,"pack_unit":"pcs"},
  {"medicinecode":"4123499","medicinename":"Champix","pack_quantity":200,"pack_unit":"pcs"},
  {"medicinecode":"4123257","medicinename":"Chloorcyclizine","pack_quantity":50,"pack_unit":"pcs"},
  {"medicinecode":"4123376","medicinename":"Chloordiazepoxide","pack_quantity":100,"pack_unit":"pcs"},
  {"medicinecode":"4123676","medicinename":"Chloorpromazine","pack_quantity":200,"pack_unit":"pcs"},
  {"medicinecode":"4123332","medicinename":"Chloorprotixeen","pack_quantity":50,"pack_unit":"pcs"},
  {"medicinecode":"4123573","medicinename":"Chloralhydraat","pack_quantity":100,"pack_unit":"pcs"},
  {"medicinecode":"4123574","medicinename":"Chloralhydraat drank fna","pack_quantity":200,"pack_unit":"pcs"},
  {"medicinecode":"4123575","medicinename":"Chloralhydraat klysma fna","pack_quantity":50,"pack_unit":"pcs"},
  {"medicinecode":"4123576","medicinename":"Chloralhydraat zetpillen fna","pack_quantity":100,"pack_unit":"pcs"},
  {"medicinecode":"4123377","medicinename":"Chlordiazepoxidum","pack_quantity":200,"pack_unit":"pcs"},
  {"medicinecode":"4123258","medicinename":"Cinnarizine","pack_quantity":50,"pack_unit":"pcs"},
  {"medicinecode":"4123200","medicinename":"Cipramil","pack_quantity":100,"pack_unit":"pcs"},
  {"medicinecode":"4123577","medicinename":"Circadin","pack_quantity":200,"pack_unit":"pcs"},
  {"medicinecode":"4123333","medicinename":"Cisordinol","pack_quantity":50,"pack_unit":"pcs"},
  {"medicinecode":"4123201","medicinename":"Citalopram","pack_quantity":100,"pack_unit":"pcs"},
  {"medicinecode":"4123259","medicinename":"Claritine","pack_quantity":200,"pack_unit":"pcs"},
  {"medicinecode":"4123260","medicinename":"Clemastine","pack_quantity":50,"pack_unit":"pcs"},
  {"medicinecode":"4123378","medicinename":"Clobazam","pack_quantity":100,"pack_unit":"pcs"},
  {"medicinecode":"4123202","medicinename":"Clomipramine","pack_quantity":200,"pack_unit":"pcs"},
  {"medicinecode":"4123379","medicinename":"Clonazepam","pack_quantity":50,"pack_unit":"pcs"},
  {"medicinecode":"4123308","medicinename":"Clonidine","pack_quantity":100,"pack_unit":"pcs"},
  {"medicinecode":"4123380","medicinename":"Clorazepinezuur","pack_quantity":200,"pack_unit":"pcs"},
  {"medicinecode":"4123334","medicinename":"Clozapine","pack_quantity":50,"pack_unit":"pcs"},
  {"medicinecode":"4123469","medicinename":"Cobimetinib","pack_quantity":100,"pack_unit":"pcs"},
  {"medicinecode":"4123517","medicinename":"Codeine","pack_quantity":200,"pack_unit":"pcs"},
  {"medicinecode":"4123518","medicinename":"Codeïne","pack_quantity":50,"pack_unit":"pcs"},
  {"medicinecode":"4123519","medicinename":"Codeïnefosfaat","pack_quantity":100,"pack_unit":"pcs"},
  {"medicinecode":"4123470","medicinename":"Cometriq","pack_quantity":200,"pack_unit":"pcs"},
  {"medicinecode":"4123644","medicinename":"Comtan","pack_quantity":5000,"pack_unit":"mg"},
  {"medicinecode":"4123126","medicinename":"Concerta","pack_quantity":100,"pack_unit":"pcs"},
  {"medicinecode":"4123645","medicinename":"Corbilta","pack_quantity":200,"pack_unit":"pcs"},
  {"medicinecode":"4123646","medicinename":"Corbilta","pack_quantity":50,"pack_unit":"pcs"},
  {"medicinecode":"4123471","medicinename":"Cotellic","pack_quantity":100,"pack_unit":"pcs"},
  {"medicinecode":"4123685","medicinename":"Cresemba","pack_quantity":200,"pack_unit":"pcs"},
  {"medicinecode":"4123578","medicinename":"Crinone","pack_quantity":50,"pack_unit":"pcs"},
  {"medicinecode":"4123472","medicinename":"Crizotinib","pack_quantity":100,"pack_unit":"pcs"},
  {"medicinecode":"4123261","medicinename":"Cyclizine","pack_quantity":200,"pack_unit":"pcs"},
  {"medicinecode":"4123262","medicinename":"Cyclizine zetpil fna","pack_quantity":50,"pack_unit":"pcs"},
  {"medicinecode":"4123579","medicinename":"Cyclogest","pack_quantity":100,"pack_unit":"pcs"},
  {"medicinecode":"4123203","medicinename":"Cymbalta","pack_quantity":200,"pack_unit":"pcs"},
  {"medicinecode":"4123647","medicinename":"Dacepton","pack_quantity":50,"pack_unit":"pcs"},
  {"medicinecode":"4123580","medicinename":"Daktarin","pack_quantity":100,"pack_unit":"pcs"},
  {"medicinecode":"4123581","medicinename":"Dantrium","pack_quantity":200,"pack_unit":"pcs"},
  {"medicinecode":"4123582","medicinename":"Dantroleen","pack_quantity":50,"pack_unit":"pcs"},
  {"medicinecode":"4123583","medicinename":"Dapoxetine","pack_quantity":100,"pack_unit":"pcs"},
  {"medicinecode":"4123442","medicinename":"Darifenacine","pack_quantity":200,"pack_unit":"pcs"},
  {"medicinecode":"4123416","medicinename":"Daro Retard dextromethorfan","pack_quantity":50,"pack_unit":"pcs"},
  {"medicinecode":"4123150","medicinename":"Depakine","pack_quantity":100,"pack_unit":"pcs"},
  {"medicinecode":"4123263","medicinename":"Desloratadine","pack_quantity":200,"pack_unit":"pcs"},
  {"medicinecode":"4123264","medicinename":"Desloratadine t/m 5 pcs","pack_quantity":50,"pack_unit":"pcs"},
  {"medicinecode":"4123443","medicinename":"Detrusitol","pack_quantity":100,"pack_unit":"pcs"},
  {"medicinecode":"4123127","medicinename":"Dexamfetamine","pack_quantity":200,"pack_unit":"pcs"},
  {"medicinecode":"4123128","medicinename":"Dexamfetamine FNA","pack_quantity":50,"pack_unit":"pcs"},
  {"medicinecode":"4123417","medicinename":"Dextromethorfan","pack_quantity":100,"pack_unit":"pcs"},
  {"medicinecode":"4123151","medicinename":"Diacomit","pack_quantity":200,"pack_unit":"pcs"},
  {"medicinecode":"4123152","medicinename":"Diamox","pack_quantity":50,"pack_unit":"pcs"},
  {"medicinecode":"4123381","medicinename":"Diazemuls","pack_quantity":100,"pack_unit":"pcs"},
  {"medicinecode":"4123382","medicinename":"Diazepam","pack_quantity":200,"pack_unit":"pcs"},
  {"medicinecode":"4123383","medicinename":"Diazepamum","pack_quantity":50,"pack_unit":"pcs"},
  {"medicinecode":"4123686","medicinename":"Diflucan","pack_quantity":100,"pack_unit":"pcs"},
  {"medicinecode":"4123265","medicinename":"Dimetindeen","pack_quantity":200,"pack_unit":"pcs"},
  {"medicinecode":"4123154","medicinename":"Diphantoïne","pack_quantity":50,"pack_unit":"pcs"},
  {"medicinecode":"4123153","medicinename":"Diphantoïne","pack_quantity":100,"pack_unit":"pcs"},
  {"medicinecode":"4123520","medicinename":"Dipidolor","pack_quantity":200,"pack_unit":"pcs"},
  {"medicinecode":"4123335","medicinename":"Dipiperon","pack_quantity":50,"pack_unit":"pcs"},
  {"medicinecode":"4123500","medicinename":"Disulfiram","pack_quantity":1000,"pack_unit":"pcs"},
  {"medicinecode":"4123309","medicinename":"Dixarit","pack_quantity":200,"pack_unit":"pcs"},
  {"medicinecode":"4123336","medicinename":"Dogmatil","pack_quantity":50,"pack_unit":"pcs"},
  {"medicinecode":"4123384","medicinename":"Dormicum","pack_quantity":100,"pack_unit":"pcs"},
  {"medicinecode":"4123385","medicinename":"Dormonoct","pack_quantity":2000,"pack_unit":"mg"},
  {"medicinecode":"4123584","medicinename":"Dostinex","pack_quantity":50,"pack_unit":"pcs"},
  {"medicinecode":"4123204","medicinename":"Dosulepine","pack_quantity":100,"pack_unit":"pcs"},
  {"medicinecode":"4123205","medicinename":"Doxepine","pack_quantity":200,"pack_unit":"pcs"},
  {"medicinecode":"4123266","medicinename":"Doxylamine/pyridoxine","pack_quantity":50,"pack_unit":"pcs"},
  {"medicinecode":"4123444","medicinename":"Dridase","pack_quantity":100,"pack_unit":"pcs"},
  {"medicinecode":"4123473","medicinename":"Dronabinol","pack_quantity":200,"pack_unit":"pcs"},
  {"medicinecode":"4123206","medicinename":"Duloxetine","pack_quantity":50,"pack_unit":"pcs"},
  {"medicinecode":"4123648","medicinename":"Duodopa","pack_quantity":100,"pack_unit":"pcs"},
  {"medicinecode":"4123521","medicinename":"Durogesic","pack_quantity":200,"pack_unit":"pcs"},
  {"medicinecode":"4123267","medicinename":"Ebastine","pack_quantity":50,"pack_unit":"pcs"},
  {"medicinecode":"4123268","medicinename":"Ebastine t/m 20 pcs","pack_quantity":100,"pack_unit":"pcs"},
  {"medicinecode":"4123139","medicinename":"Ebixa","pack_quantity":200,"pack_unit":"pcs"},
  {"medicinecode":"4123687","medicinename":"Ecalta","pack_quantity":50,"pack_unit":"pcs"},
  {"medicinecode":"4123207","medicinename":"Efexor","pack_quantity":100,"pack_unit":"pcs"},
  {"medicinecode":"4123522","medicinename":"Effentora","pack_quantity":200,"pack_unit":"pcs"},
  {"medicinecode":"4123426","medicinename":"Eletriptan","pack_quantity":50,"pack_unit":"pcs"},
  {"medicinecode":"4123129","medicinename":"Elvanse","pack_quantity":100,"pack_unit":"pcs"},
  {"medicinecode":"4123269","medicinename":"Emesafene","pack_quantity":200,"pack_unit":"pcs"},
  {"medicinecode":"4123445","medicinename":"Emselex","pack_quantity":50,"pack_unit":"pcs"},
  {"medicinecode":"4123649","medicinename":"Entacapon","pack_quantity":100,"pack_unit":"pcs"},
  {"medicinecode":"4123155","medicinename":"Epanutin","pack_quantity":200,"pack_unit":"pcs"},
  {"medicinecode":"4123130","medicinename":"Equasym XL","pack_quantity":50,"pack_unit":"pcs"},
  {"medicinecode":"4123585","medicinename":"Eravacycline","pack_quantity":100,"pack_unit":"pcs"},
  {"medicinecode":"4123474","medicinename":"Erivedge","pack_quantity":200,"pack_unit":"pcs"},
  {"medicinecode":"4123208","medicinename":"Escitalopram","pack_quantity":50,"pack_unit":"pcs"},
  {"medicinecode":"4123209","medicinename":"Esketamine nasaal","pack_quantity":100,"pack_unit":"pcs"},
  {"medicinecode":"4123156","medicinename":"Ethosuximide","pack_quantity":200,"pack_unit":"pcs"},
  {"medicinecode":"4123157","medicinename":"Ethymal","pack_quantity":50,"pack_unit":"pcs"},
  {"medicinecode":"4123140","medicinename":"Exelon","pack_quantity":100,"pack_unit":"pcs"},
  {"medicinecode":"4123158","medicinename":"Felbamaat","pack_quantity":200,"pack_unit":"pcs"},
  {"medicinecode":"4123210","medicinename":"Fenelzine","pack_quantity":50,"pack_unit":"pcs"},
  {"medicinecode":"4123270","medicinename":"Fenistil","pack_quantity":100,"pack_unit":"pcs"},
  {"medicinecode":"4123159","medicinename":"Fenobarbital","pack_quantity":200,"pack_unit":"pcs"},
  {"medicinecode":"4123160","medicinename":"Fenobarbital drank FNA","pack_quantity":50,"pack_unit":"pcs"},
  {"medicinecode":"4123523","medicinename":"Fentanyl","pack_quantity":100,"pack_unit":"pcs"},
  {"medicinecode":"4123161","medicinename":"Fenytoine","pack_quantity":200,"pack_unit":"pcs"},
  {"medicinecode":"4123162","medicinename":"Fenytoïne suspensie FNA","pack_quantity":50,"pack_unit":"pcs"},
  {"medicinecode":"4123446","medicinename":"Fesoterodine","pack_quantity":100,"pack_unit":"pcs"},
  {"medicinecode":"4123211","medicinename":"Fevarin","pack_quantity":200,"pack_unit":"pcs"},
  {"medicinecode":"4123271","medicinename":"Fexofenadine","pack_quantity":50,"pack_unit":"pcs"},
  {"medicinecode":"4123272","medicinename":"Fexofenadine t/m 240 pcs","pack_quantity":100,"pack_unit":"pcs"},
  {"medicinecode":"4123447","medicinename":"Flavoxaat","pack_quantity":200,"pack_unit":"pcs"},
  {"medicinecode":"4123337","medicinename":"Fluanxol","pack_quantity":50,"pack_unit":"pcs"},
  {"medicinecode":"4123688","medicinename":"Fluconazol","pack_quantity":100,"pack_unit":"pcs"},
  {"medicinecode":"4123689","medicinename":"flucytosine","pack_quantity":200,"pack_unit":"pcs"},
  {"medicinecode":"4123427","medicinename":"Flunarizine","pack_quantity":50,"pack_unit":"pcs"},
  {"medicinecode":"4123386","medicinename":"Flunitrazepam","pack_quantity":1000,"pack_unit":"mg"},
  {"medicinecode":"4123212","medicinename":"Fluoxetine","pack_quantity":200,"pack_unit":"pcs"},
  {"medicinecode":"4123338","medicinename":"Flupentixol","pack_quantity":50,"pack_unit":"pcs"},
  {"medicinecode":"4123387","medicinename":"Flurazepam","pack_quantity":100,"pack_unit":"pcs"},
  {"medicinecode":"4123388","medicinename":"Flurazepam hydrochloridum","pack_quantity":200,"pack_unit":"pcs"},
  {"medicinecode":"4123339","medicinename":"Fluspirileen","pack_quantity":50,"pack_unit":"pcs"},
  {"medicinecode":"4123213","medicinename":"Fluvoxamine","pack_quantity":100,"pack_unit":"pcs"},
  {"medicinecode":"4123214","medicinename":"Fluvoxaminemaleaat","pack_quantity":200,"pack_unit":"pcs"},
  {"medicinecode":"4123389","medicinename":"Frisium","pack_quantity":50,"pack_unit":"pcs"},
  {"medicinecode":"4123428","medicinename":"Fromirex","pack_quantity":100,"pack_unit":"pcs"},
  {"medicinecode":"4123429","medicinename":"Frovatriptan","pack_quantity":200,"pack_unit":"pcs"},
  {"medicinecode":"4123586","medicinename":"Fungizone","pack_quantity":50,"pack_unit":"pcs"},
  {"medicinecode":"4123163","medicinename":"Fycompa","pack_quantity":100,"pack_unit":"pcs"},
  {"medicinecode":"4123164","medicinename":"Gabapentine","pack_quantity":200,"pack_unit":"pcs"},
  {"medicinecode":"4123501","medicinename":"Gablofen","pack_quantity":50,"pack_unit":"pcs"},
  {"medicinecode":"4123141","medicinename":"Galantamine","pack_quantity":100,"pack_unit":"pcs"},
  {"medicinecode":"4123587","medicinename":"GHB","pack_quantity":200,"pack_unit":"pcs"},
  {"medicinecode":"4123475","medicinename":"Giotrif","pack_quantity":50,"pack_unit":"pcs"},
  {"medicinecode":"4123588","medicinename":"Glentek","pack_quantity":100,"pack_unit":"pcs"},
  {"medicinecode":"4123650","medicinename":"Glepark","pack_quantity":200,"pack_unit":"pcs"},
  {"medicinecode":"4123651","medicinename":"Glycopyrronium drank","pack_quantity":50,"pack_unit":"pcs"},
  {"medicinecode":"4123690","medicinename":"Griseofulvine","pack_quantity":100,"pack_unit":"pcs"},
  {"medicinecode":"4123691","medicinename":"Griseofulvine suspensie FNA","pack_quantity":200,"pack_unit":"pcs"},
  {"medicinecode":"4123340","medicinename":"Haldol","pack_quantity":50,"pack_unit":"pcs"},
  {"medicinecode":"4123341","medicinename":"Haloperidol","pack_quantity":100,"pack_unit":"pcs"},
  {"medicinecode":"4123310","medicinename":"Hemangiol","pack_quantity":200,"pack_unit":"pcs"},
  {"medicinecode":"4123589","medicinename":"Holland & Barrett Valeriaan","pack_quantity":50,"pack_unit":"pcs"},
  {"medicinecode":"4123273","medicinename":"Hooikoortstablet cetirizine","pack_quantity":100,"pack_unit":"pcs"},
  {"medicinecode":"4123274","medicinename":"Hooikoortstablet loratadine","pack_quantity":200,"pack_unit":"pcs"},
  {"medicinecode":"4123524","medicinename":"Hydromorfon","pack_quantity":50,"pack_unit":"pcs"},
  {"medicinecode":"4123590","medicinename":"Hydroxyboterzuur","pack_quantity":100,"pack_unit":"pcs"},
  {"medicinecode":"4123275","medicinename":"Hydroxyzine","pack_quantity":200,"pack_unit":"pcs"},
  {"medicinecode":"4123476","medicinename":"Ibrance","pack_quantity":50,"pack_unit":"pcs"},
  {"medicinecode":"4123477","medicinename":"Idelalisib","pack_quantity":100,"pack_unit":"pcs"},
  {"medicinecode":"4123342","medicinename":"Imap","pack_quantity":200,"pack_unit":"pcs"},
  {"medicinecode":"4123430","medicinename":"Imigran","pack_quantity":50,"pack_unit":"pcs"},
  {"medicinecode":"4123215","medicinename":"Imipramine","pack_quantity":100,"pack_unit":"pcs"},
  {"medicinecode":"4123390","medicinename":"Imovane","pack_quantity":200,"pack_unit":"pcs"},
  {"medicinecode":"4123343","medicinename":"Impromen","pack_quantity":50,"pack_unit":"pcs"},
  {"medicinecode":"4123591","medicinename":"Indocollyre","pack_quantity":100,"pack_unit":"pcs"},
  {"medicinecode":"4123592","medicinename":"Indometacine","pack_quantity":200,"pack_unit":"pcs"},
  {"medicinecode":"4123478","medicinename":"Inlyta","pack_quantity":50,"pack_unit":"pcs"},
  {"medicinecode":"4123525","medicinename":"Instanyl","pack_quantity":100,"pack_unit":"pcs"},
  {"medicinecode":"4123344","medicinename":"Invega","pack_quantity":200,"pack_unit":"pcs"},
  {"medicinecode":"4123692","medicinename":"Isavuconazol","pack_quantity":50,"pack_unit":"pcs"},
  {"medicinecode":"4123593","medicinename":"Itraconazol","pack_quantity":100,"pack_unit":"pcs"},
  {"medicinecode":"4123479","medicinename":"Ixazomib","pack_quantity":200,"pack_unit":"pcs"},
  {"medicinecode":"4123526","medicinename":"Kapanol","pack_quantity":50,"pack_unit":"pcs"},
  {"medicinecode":"4123448","medicinename":"Kentera","pack_quantity":100,"pack_unit":"pcs"},
  {"medicinecode":"4123165","medicinename":"Keppra","pack_quantity":200,"pack_unit":"pcs"},
  {"medicinecode":"4123276","medicinename":"Kestine","pack_quantity":50,"pack_unit":"pcs"},
  {"medicinecode":"4123594","medicinename":"Ketoconazol","pack_quantity":100,"pack_unit":"pcs"},
  {"medicinecode":"4123595","medicinename":"Ketoconazol HRA","pack_quantity":200,"pack_unit":"pcs"},
  {"medicinecode":"4123277","medicinename":"Ketotifen","pack_quantity":50,"pack_unit":"pcs"},
  {"medicinecode":"4123278","medicinename":"Ketotifen (oog)","pack_quantity":1000,"pack_unit":"ml"},
  {"medicinecode":"4123166","medicinename":"Kevesy","pack_quantity":200,"pack_unit":"pcs"},
  {"medicinecode":"4123131","medicinename":"Kinecteen","pack_quantity":5000,"pack_unit":"mg"},
  {"medicinecode":"4123480","medicinename":"Kisqali","pack_quantity":100,"pack_unit":"pcs"},
  {"medicinecode":"4123481","medicinename":"Kyprolis","pack_quantity":200,"pack_unit":"pcs"},
  {"medicinecode":"4123167","medicinename":"Lacosamide","pack_quantity":50,"pack_unit":"pcs"},
  {"medicinecode":"4123596","medicinename":"Lamberts Valeriaan","pack_quantity":100,"pack_unit":"pcs"},
  {"medicinecode":"4123168","medicinename":"Lamictal","pack_quantity":200,"pack_unit":"pcs"},
  {"medicinecode":"4123169","medicinename":"Lamotrigine","pack_quantity":50,"pack_unit":"pcs"},
  {"medicinecode":"4123345","medicinename":"Latuda","pack_quantity":100,"pack_unit":"pcs"},
  {"medicinecode":"4123597","medicinename":"Leflunomide","pack_quantity":200,"pack_unit":"pcs"},
  {"medicinecode":"4123482","medicinename":"Lenalidomide","pack_quantity":50,"pack_unit":"pcs"},
  {"medicinecode":"4123391","medicinename":"Lendormin","pack_quantity":100,"pack_unit":"pcs"},
  {"medicinecode":"4123346","medicinename":"Leponex","pack_quantity":200,"pack_unit":"pcs"},
  {"medicinecode":"4123170","medicinename":"Levetiracetam","pack_quantity":50,"pack_unit":"pcs"},
  {"medicinecode":"4123279","medicinename":"Levocetirizine","pack_quantity":100,"pack_unit":"pcs"},
  {"medicinecode":"4123280","medicinename":"Levocetirizine t/m 5 pcs","pack_quantity":200,"pack_unit":"pcs"},
  {"medicinecode":"4123652","medicinename":"Levodopa","pack_quantity":50,"pack_unit":"pcs"},
  {"medicinecode":"4123653","medicinename":"Levodopa/Carbidopa","pack_quantity":100,"pack_unit":"pcs"},
  {"medicinecode":"4123598","medicinename":"Levomepromazine","pack_quantity":200,"pack_unit":"pcs"},
  {"medicinecode":"4123216","medicinename":"Lexapro","pack_quantity":50,"pack_unit":"pcs"},
  {"medicinecode":"4123502","medicinename":"Lioresal","pack_quantity":1000,"pack_unit":"mg"},
  {"medicinecode":"4123132","medicinename":"Lisdexamfetamine","pack_quantity":200,"pack_unit":"pcs"},
  {"medicinecode":"4123217","medicinename":"Lithium","pack_quantity":50,"pack_unit":"pcs"},
  {"medicinecode":"4123218","medicinename":"Lithiumcarbonaat","pack_quantity":100,"pack_unit":"pcs"},
  {"medicinecode":"4123219","medicinename":"Lithiumcarbonaat capsules FNA","pack_quantity":200,"pack_unit":"pcs"},
  {"medicinecode":"4123392","medicinename":"Loprazolam","pack_quantity":50,"pack_unit":"pcs"},
  {"medicinecode":"4123281","medicinename":"Loratadine","pack_quantity":100,"pack_unit":"pcs"},
  {"medicinecode":"4123282","medicinename":"Loratadine t/m 10 pcs","pack_quantity":200,"pack_unit":"pcs"},
  {"medicinecode":"4123393","medicinename":"Lorazepam","pack_quantity":50,"pack_unit":"pcs"},
  {"medicinecode":"4123394","medicinename":"Lorazepam drank FNA","pack_quantity":100,"pack_unit":"pcs"},
  {"medicinecode":"4123395","medicinename":"Lormetazepam","pack_quantity":200,"pack_unit":"pcs"},
  {"medicinecode":"4123347","medicinename":"Lurasidon","pack_quantity":50,"pack_unit":"pcs"},
  {"medicinecode":"4123599","medicinename":"Lutinus","pack_quantity":100,"pack_unit":"pcs"},
  {"medicinecode":"4123171","medicinename":"Lyrica","pack_quantity":200,"pack_unit":"pcs"},
  {"medicinecode":"4123654","medicinename":"Madopar","pack_quantity":50,"pack_unit":"pcs"},
  {"medicinecode":"4123220","medicinename":"Maprotiline","pack_quantity":100,"pack_unit":"pcs"},
  {"medicinecode":"4123527","medicinename":"Maracex","pack_quantity":200,"pack_unit":"pcs"},
  {"medicinecode":"4123600","medicinename":"Marihuana, medicinaal","pack_quantity":50,"pack_unit":"pcs"},
  {"medicinecode":"4123483","medicinename":"Marinol","pack_quantity":100,"pack_unit":"pcs"},
  {"medicinecode":"4123172","medicinename":"Matever","pack_quantity":200,"pack_unit":"pcs"},
  {"medicinecode":"4123431","medicinename":"Maxalt","pack_quantity":50,"pack_unit":"pcs"},
  {"medicinecode":"4123283","medicinename":"Meclozine","pack_quantity":100,"pack_unit":"pcs"},
  {"medicinecode":"4123133","medicinename":"Medikinet","pack_quantity":200,"pack_unit":"pcs"},
  {"medicinecode":"4123134","medicinename":"Medikinet CR","pack_quantity":50,"pack_unit":"pcs"},
  {"medicinecode":"4123484","medicinename":"Mektovi","pack_quantity":100,"pack_unit":"pcs"},
  {"medicinecode":"4123601","medicinename":"Melatonine","pack_quantity":200,"pack_unit":"pcs"},
  {"medicinecode":"4123142","medicinename":"Memantine","pack_quantity":50,"pack_unit":"pcs"},
  {"medicinecode":"4123528","medicinename":"Methadon","pack_quantity":100,"pack_unit":"pcs"},
  {"medicinecode":"4123529","medicinename":"Methadon drank FNA","pack_quantity":200,"pack_unit":"pcs"},
  {"medicinecode":"4123530","medicinename":"Methadon tablet","pack_quantity":50,"pack_unit":"pcs"},
  {"medicinecode":"4123311","medicinename":"Methyldopa","pack_quantity":1000,"pack_unit":"ml"},
  {"medicinecode":"4123135","medicinename":"Methylfenidaat","pack_quantity":200,"pack_unit":"pcs"},
  {"medicinecode":"4123677","medicinename":"Metoclopramide","pack_quantity":50,"pack_unit":"pcs"},
  {"medicinecode":"4123312","medicinename":"Metoprolol","pack_quantity":100,"pack_unit":"pcs"},
  {"medicinecode":"4123313","medicinename":"Metoprolol/Hydrochloorthiazide","pack_quantity":200,"pack_unit":"pcs"},
  {"medicinecode":"4123314","medicinename":"Metoprololi Succinas","pack_quantity":50,"pack_unit":"pcs"},
  {"medicinecode":"4123315","medicinename":"Metoprololi Tartras","pack_quantity":100,"pack_unit":"pcs"},
  {"medicinecode":"4123316","medicinename":"Metoprololsuccinaat","pack_quantity":200,"pack_unit":"pcs"},
  {"medicinecode":"4123317","medicinename":"Metoprololtartraat","pack_quantity":50,"pack_unit":"pcs"},
  {"medicinecode":"4123221","medicinename":"Mianserine","pack_quantity":100,"pack_unit":"pcs"},
  {"medicinecode":"4123693","medicinename":"Micafungine","pack_quantity":200,"pack_unit":"pcs"},
  {"medicinecode":"4123602","medicinename":"Miconazol","pack_quantity":50,"pack_unit":"pcs"},
  {"medicinecode":"4123396","medicinename":"Midazolam","pack_quantity":100,"pack_unit":"pcs"},
  {"medicinecode":"4123678","medicinename":"Migrafin","pack_quantity":200,"pack_unit":"pcs"},
  {"medicinecode":"4123655","medicinename":"Mirapexin","pack_quantity":50,"pack_unit":"pcs"},
  {"medicinecode":"4123222","medicinename":"Mirtazapine","pack_quantity":100,"pack_unit":"pcs"},
  {"medicinecode":"4123284","medicinename":"Mizolastine t/m 10 pcs","pack_quantity":200,"pack_unit":"pcs"},
  {"medicinecode":"4123285","medicinename":"Mizollen","pack_quantity":50,"pack_unit":"pcs"},
  {"medicinecode":"4123223","medicinename":"Moclobemide","pack_quantity":100,"pack_unit":"pcs"},
  {"medicinecode":"4123603","medicinename":"Modafinil","pack_quantity":2000,"pack_unit":"ml"},
  {"medicinecode":"4123604","medicinename":"Modiodal","pack_quantity":50,"pack_unit":"pcs"},
  {"medicinecode":"4123397","medicinename":"Mogadon","pack_quantity":100,"pack_unit":"pcs"},
  {"medicinecode":"4123531","medicinename":"Morfine","pack_quantity":200,"pack_unit":"pcs"},
  {"medicinecode":"4123532","medicinename":"Morfine drank FNA","pack_quantity":50,"pack_unit":"pcs"},
  {"medicinecode":"4123533","medicinename":"Morfine zetpillen FNA","pack_quantity":100,"pack_unit":"pcs"},
  {"medicinecode":"4123534","medicinename":"Morfinesulfaat","pack_quantity":200,"pack_unit":"pcs"},
  {"medicinecode":"4123318","medicinename":"Moxonidine","pack_quantity":50,"pack_unit":"pcs"},
  {"medicinecode":"4123535","medicinename":"MS Contin","pack_quantity":100,"pack_unit":"pcs"},
  {"medicinecode":"4123694","medicinename":"Mycamine","pack_quantity":200,"pack_unit":"pcs"},
  {"medicinecode":"4123503","medicinename":"Mysimba","pack_quantity":50,"pack_unit":"pcs"},
  {"medicinecode":"4123173","medicinename":"Mysoline","pack_quantity":100,"pack_unit":"pcs"},
  {"medicinecode":"4123536","medicinename":"Nalbufine","pack_quantity":200,"pack_unit":"pcs"},
  {"medicinecode":"4123504","medicinename":"Naltrexon","pack_quantity":50,"pack_unit":"pcs"},
  {"medicinecode":"4123432","medicinename":"Naramig","pack_quantity":100,"pack_unit":"pcs"},
  {"medicinecode":"4123433","medicinename":"Naratriptan","pack_quantity":200,"pack_unit":"pcs"},
  {"medicinecode":"4123224","medicinename":"Nardil","pack_quantity":50,"pack_unit":"pcs"},
  {"medicinecode":"4123605","medicinename":"Natriumoxybaat","pack_quantity":100,"pack_unit":"pcs"},
  {"medicinecode":"4123174","medicinename":"Natriumvalproaat","pack_quantity":200,"pack_unit":"pcs"},
  {"medicinecode":"4123418","medicinename":"Natterman Noscasan","pack_quantity":50,"pack_unit":"pcs"},
  {"medicinecode":"4123286","medicinename":"Nedeltran","pack_quantity":100,"pack_unit":"pcs"},
  {"medicinecode":"4123143","medicinename":"Nemdatine","pack_quantity":2000,"pack_unit":"ml"},
  {"medicinecode":"4123287","medicinename":"Neoclarityn","pack_quantity":50,"pack_unit":"pcs"},
  {"medicinecode":"4123656","medicinename":"Neupro","pack_quantity":100,"pack_unit":"pcs"},
  {"medicinecode":"4123175","medicinename":"Neurotin","pack_quantity":200,"pack_unit":"pcs"},
  {"medicinecode":"4123485","medicinename":"Ninlaro","pack_quantity":50,"pack_unit":"pcs"},
  {"medicinecode":"4123398","medicinename":"Nitrazepam","pack_quantity":100,"pack_unit":"pcs"},
  {"medicinecode":"4123606","medicinename":"Nootropil","pack_quantity":200,"pack_unit":"pcs"},
  {"medicinecode":"4123399","medicinename":"Normison","pack_quantity":50,"pack_unit":"pcs"},
  {"medicinecode":"4123607","medicinename":"Norprolac","pack_quantity":100,"pack_unit":"pcs"},
  {"medicinecode":"4123225","medicinename":"Nortrilen","pack_quantity":200,"pack_unit":"pcs"},
  {"medicinecode":"4123226","medicinename":"Nortriptyline","pack_quantity":50,"pack_unit":"pcs"},
  {"medicinecode":"4123419","medicinename":"Noscapect Roter","pack_quantity":100,"pack_unit":"pcs"},
  {"medicinecode":"4123420","medicinename":"Noscapine","pack_quantity":200,"pack_unit":"pcs"},
  {"medicinecode":"4123608","medicinename":"Noxafil","pack_quantity":50,"pack_unit":"pcs"},
  {"medicinecode":"4123609","medicinename":"Nozinan","pack_quantity":1000,"pack_unit":"mg"},
  {"medicinecode":"4123695","medicinename":"Nystatine","pack_quantity":200,"pack_unit":"pcs"},
  {"medicinecode":"4123348","medicinename":"Olanzapine","pack_quantity":50,"pack_unit":"pcs"},
  {"medicinecode":"4123657","medicinename":"Oprymea","pack_quantity":100,"pack_unit":"pcs"},
  {"medicinecode":"4123537","medicinename":"Oramorph","pack_quantity":200,"pack_unit":"pcs"},
  {"medicinecode":"4123349","medicinename":"Orap","pack_quantity":50,"pack_unit":"pcs"},
  {"medicinecode":"4123176","medicinename":"Orfiril","pack_quantity":100,"pack_unit":"pcs"},
  {"medicinecode":"4123421","medicinename":"Otrivin Noscapine","pack_quantity":200,"pack_unit":"pcs"},
  {"medicinecode":"4123400","medicinename":"Oxazepam","pack_quantity":50,"pack_unit":"pcs"},
  {"medicinecode":"4123177","medicinename":"Oxcarbazepine","pack_quantity":1000,"pack_unit":"ml"},
  {"medicinecode":"4123422","medicinename":"Oxomemazine","pack_quantity":200,"pack_unit":"pcs"},
  {"medicinecode":"4123449","medicinename":"Oxybutynine","pack_quantity":50,"pack_unit":"pcs"},
  {"medicinecode":"4123538","medicinename":"Oxycodon","pack_quantity":100,"pack_unit":"pcs"},
  {"medicinecode":"4123539","medicinename":"Oxycontin","pack_quantity":200,"pack_unit":"pcs"},
  {"medicinecode":"4123540","medicinename":"Oxynorm","pack_quantity":50,"pack_unit":"pcs"},
  {"medicinecode":"4123486","medicinename":"Palbociclib","pack_quantity":100,"pack_unit":"pcs"},
  {"medicinecode":"4123541","medicinename":"Palexia","pack_quantity":200,"pack_unit":"pcs"},
  {"medicinecode":"4123350","medicinename":"Paliperidon","pack_quantity":50,"pack_unit":"pcs"},
  {"medicinecode":"4123542","medicinename":"Palladon","pack_quantity":100,"pack_unit":"pcs"},
  {"medicinecode":"4123658","medicinename":"Parlodel","pack_quantity":200,"pack_unit":"pcs"},
  {"medicinecode":"4123227","medicinename":"Parnate","pack_quantity":50,"pack_unit":"pcs"},
  {"medicinecode":"4123228","medicinename":"Paroxetine","pack_quantity":100,"pack_unit":"pcs"},
  {"medicinecode":"4123229","medicinename":"Paroxetinum","pack_quantity":200,"pack_unit":"pcs"},
  {"medicinecode":"4123543","medicinename":"Pecfent","pack_quantity":50,"pack_unit":"pcs"},
  {"medicinecode":"4123351","medicinename":"Penfluridol","pack_quantity":100,"pack_unit":"pcs"},
  {"medicinecode":"4123178","medicinename":"Perampanel","pack_quantity":200,"pack_unit":"pcs"},
  {"medicinecode":"4123659","medicinename":"Pergolide","pack_quantity":50,"pack_unit":"pcs"},
  {"medicinecode":"4123660","medicinename":"Permax","pack_quantity":100,"pack_unit":"pcs"},
  {"medicinecode":"4123544","medicinename":"Pethidine","pack_quantity":200,"pack_unit":"pcs"},
  {"medicinecode":"4123179","medicinename":"Phenobarbital","pack_quantity":50,"pack_unit":"pcs"},
  {"medicinecode":"4123352","medicinename":"Pimozide","pack_quantity":100,"pack_unit":"pcs"},
  {"medicinecode":"4123353","medicinename":"Pipamperon","pack_quantity":200,"pack_unit":"pcs"},
  {"medicinecode":"4123487","medicinename":"Piqray","pack_quantity":50,"pack_unit":"pcs"},
  {"medicinecode":"4123610","medicinename":"Piracetam","pack_quantity":100,"pack_unit":"pcs"},
  {"medicinecode":"4123545","medicinename":"Piritramide","pack_quantity":200,"pack_unit":"pcs"},
  {"medicinecode":"4123434","medicinename":"Pizotifeen","pack_quantity":500,"pack_unit":"mg"},
  {"medicinecode":"4123611","medicinename":"Plantival","pack_quantity":100,"pack_unit":"pcs"},
  {"medicinecode":"4123612","medicinename":"Posaconazol","pack_quantity":200,"pack_unit":"pcs"},
  {"medicinecode":"4123661","medicinename":"Pramipexol","pack_quantity":50,"pack_unit":"pcs"},
  {"medicinecode":"4123401","medicinename":"Prazepam","pack_quantity":100,"pack_unit":"pcs"},
  {"medicinecode":"4123613","medicinename":"Praziquantel","pack_quantity":200,"pack_unit":"pcs"},
  {"medicinecode":"4123180","medicinename":"Pregabaline","pack_quantity":50,"pack_unit":"pcs"},
  {"medicinecode":"4123288","medicinename":"Prevalin Allerstop","pack_quantity":100,"pack_unit":"pcs"},
  {"medicinecode":"4123230","medicinename":"Priadel","pack_quantity":200,"pack_unit":"pcs"},
  {"medicinecode":"4123614","medicinename":"Prialt","pack_quantity":50,"pack_unit":"pcs"},
  {"medicinecode":"4123615","medicinename":"Priligy","pack_quantity":100,"pack_unit":"pcs"},
  {"medicinecode":"4123289","medicinename":"Primatour","pack_quantity":200,"pack_unit":"pcs"},
  {"medicinecode":"4123181","medicinename":"Primidon","pack_quantity":50,"pack_unit":"pcs"},
  {"medicinecode":"4123679","medicinename":"Primperan","pack_quantity":100,"pack_unit":"pcs"},
  {"medicinecode":"4123616","medicinename":"Progesteron","pack_quantity":200,"pack_unit":"pcs"},
  {"medicinecode":"4123290","medicinename":"Promethazine","pack_quantity":50,"pack_unit":"pcs"},
  {"medicinecode":"4123291","medicinename":"Promethazine comp.","pack_quantity":100,"pack_unit":"pcs"},
  {"medicinecode":"4123319","medicinename":"Propranolol","pack_quantity":200,"pack_unit":"pcs"},
  {"medicinecode":"4123320","medicinename":"Propranolol drank FNA","pack_quantity":50,"pack_unit":"pcs"},
  {"medicinecode":"4123231","medicinename":"Prothiaden","pack_quantity":100,"pack_unit":"pcs"},
  {"medicinecode":"4123232","medicinename":"Prozac","pack_quantity":2000,"pack_unit":"mg"},
  {"medicinecode":"4123354","medicinename":"Quetiapine","pack_quantity":50,"pack_unit":"pcs"},
  {"medicinecode":"4123617","medicinename":"Quinagolide","pack_quantity":100,"pack_unit":"pcs"},
  {"medicinecode":"4123546","medicinename":"Rapifen","pack_quantity":200,"pack_unit":"pcs"},
  {"medicinecode":"4123662","medicinename":"Rasagiline","pack_quantity":50,"pack_unit":"pcs"},
  {"medicinecode":"4123292","medicinename":"Reactine","pack_quantity":100,"pack_unit":"pcs"},
  {"medicinecode":"4123355","medicinename":"Reagila","pack_quantity":200,"pack_unit":"pcs"},
  {"medicinecode":"4123402","medicinename":"Reapam","pack_quantity":50,"pack_unit":"pcs"},
  {"medicinecode":"4123547","medicinename":"Recivit","pack_quantity":100,"pack_unit":"pcs"},
  {"medicinecode":"4123505","medicinename":"Refusal","pack_quantity":200,"pack_unit":"pcs"},
  {"medicinecode":"4123435","medicinename":"Relpax","pack_quantity":50,"pack_unit":"pcs"},
  {"medicinecode":"4123233","medicinename":"Remeron","pack_quantity":100,"pack_unit":"pcs"},
  {"medicinecode":"4123548","medicinename":"Remifentanil","pack_quantity":200,"pack_unit":"pcs"},
  {"medicinecode":"4123403","medicinename":"Remimazolam","pack_quantity":50,"pack_unit":"pcs"},
  {"medicinecode":"4123144","medicinename":"Reminyl","pack_quantity":100,"pack_unit":"pcs"},
  {"medicinecode":"4123663","medicinename":"Requip","pack_quantity":200,"pack_unit":"pcs"},
  {"medicinecode":"4123488","medicinename":"Revlimid","pack_quantity":50,"pack_unit":"pcs"},
  {"medicinecode":"4123489","medicinename":"Ribociclib","pack_quantity":100,"pack_unit":"pcs"},
  {"medicinecode":"4123618","medicinename":"Rilutek","pack_quantity":200,"pack_unit":"pcs"},
  {"medicinecode":"4123619","medicinename":"Riluzol","pack_quantity":50,"pack_unit":"pcs"},
  {"medicinecode":"4123356","medicinename":"Risperdal","pack_quantity":100,"pack_unit":"pcs"},
  {"medicinecode":"4123357","medicinename":"Risperidon","pack_quantity":200,"pack_unit":"pcs"},
  {"medicinecode":"4123136","medicinename":"Ritalin","pack_quantity":50,"pack_unit":"pcs"},
  {"medicinecode":"4123145","medicinename":"Rivastigmine","pack_quantity":100,"pack_unit":"pcs"},
  {"medicinecode":"4123404","medicinename":"Rivotril","pack_quantity":200,"pack_unit":"pcs"},
  {"medicinecode":"4123436","medicinename":"Rizatriptan","pack_quantity":50,"pack_unit":"pcs"},
  {"medicinecode":"4123664","medicinename":"Ropinirol","pack_quantity":100,"pack_unit":"pcs"},
  {"medicinecode":"4123665","medicinename":"Rotigotine","pack_quantity":200,"pack_unit":"pcs"},
  {"medicinecode":"4123293","medicinename":"Rupafin","pack_quantity":50,"pack_unit":"pcs"},
  {"medicinecode":"4123294","medicinename":"Rupatadine","pack_quantity":1000,"pack_unit":"ml"},
  {"medicinecode":"4123295","medicinename":"Rupatadine t/m 10pcs","pack_quantity":200,"pack_unit":"pcs"},
  {"medicinecode":"4123358","medicinename":"Rxulti","pack_quantity":50,"pack_unit":"pcs"},
  {"medicinecode":"4123182","medicinename":"Sabril","pack_quantity":100,"pack_unit":"pcs"},
  {"medicinecode":"4123666","medicinename":"safinamide","pack_quantity":200,"pack_unit":"pcs"},
  {"medicinecode":"4123437","medicinename":"Sandomigran","pack_quantity":50,"pack_unit":"pcs"},
  {"medicinecode":"4123620","medicinename":"Scopoderm","pack_quantity":100,"pack_unit":"pcs"},
  {"medicinecode":"4123621","medicinename":"Scopolamine","pack_quantity":200,"pack_unit":"pcs"},
  {"medicinecode":"4123667","medicinename":"Selegiline","pack_quantity":50,"pack_unit":"pcs"},
  {"medicinecode":"4123321","medicinename":"Selokeen","pack_quantity":100,"pack_unit":"pcs"},
  {"medicinecode":"4123322","medicinename":"Selokomb","pack_quantity":200,"pack_unit":"pcs"},
  {"medicinecode":"4123296","medicinename":"Semprex","pack_quantity":50,"pack_unit":"pcs"},
  {"medicinecode":"4123549","medicinename":"Sendolor","pack_quantity":100,"pack_unit":"pcs"},
  {"medicinecode":"4123359","medicinename":"Serdolect","pack_quantity":200,"pack_unit":"pcs"},
  {"medicinecode":"4123405","medicinename":"Seresta","pack_quantity":50,"pack_unit":"pcs"},
  {"medicinecode":"4123360","medicinename":"Seroquel","pack_quantity":100,"pack_unit":"pcs"},
  {"medicinecode":"4123234","medicinename":"Seroxat","pack_quantity":200,"pack_unit":"pcs"},
  {"medicinecode":"4123361","medicinename":"Sertindol","pack_quantity":50,"pack_unit":"pcs"},
  {"medicinecode":"4123235","medicinename":"Sertraline","pack_quantity":100,"pack_unit":"pcs"},
  {"medicinecode":"4123668","medicinename":"Sialanar","pack_quantity":200,"pack_unit":"pcs"},
  {"medicinecode":"4123438","medicinename":"Sibelium","pack_quantity":50,"pack_unit":"pcs"},
  {"medicinecode":"4123669","medicinename":"Sifrol","pack_quantity":100,"pack_unit":"pcs"},
  {"medicinecode":"4123670","medicinename":"Sinemet","pack_quantity":200,"pack_unit":"pcs"},
  {"medicinecode":"4123236","medicinename":"Sinequan","pack_quantity":50,"pack_unit":"pcs"},
  {"medicinecode":"4123622","medicinename":"Sirdalud","pack_quantity":100,"pack_unit":"pcs"},
  {"medicinecode":"4123450","medicinename":"Solifenacine","pack_quantity":2000,"pack_unit":"ml"},
  {"medicinecode":"4123237","medicinename":"Spravato","pack_quantity":50,"pack_unit":"pcs"},
  {"medicinecode":"4123671","medicinename":"Stalevo","pack_quantity":100,"pack_unit":"pcs"},
  {"medicinecode":"4123672","medicinename":"Stalevo","pack_quantity":200,"pack_unit":"pcs"},
  {"medicinecode":"4123406","medicinename":"Stesolid","pack_quantity":50,"pack_unit":"pcs"},
  {"medicinecode":"4123407","medicinename":"Stilnoct","pack_quantity":100,"pack_unit":"pcs"},
  {"medicinecode":"4123183","medicinename":"Stiripentol","pack_quantity":200,"pack_unit":"pcs"},
  {"medicinecode":"4123137","medicinename":"Strattera","pack_quantity":50,"pack_unit":"pcs"},
  {"medicinecode":"4123550","medicinename":"Suboxone","pack_quantity":100,"pack_unit":"pcs"},
  {"medicinecode":"4123551","medicinename":"Sufenta","pack_quantity":200,"pack_unit":"pcs"},
  {"medicinecode":"4123552","medicinename":"Sufenta Forte","pack_quantity":50,"pack_unit":"pcs"},
  {"medicinecode":"4123553","medicinename":"Sufentanil","pack_quantity":100,"pack_unit":"pcs"},
  {"medicinecode":"4123362","medicinename":"Sulpiride","pack_quantity":200,"pack_unit":"pcs"},
  {"medicinecode":"4123439","medicinename":"Sumatriptan","pack_quantity":50,"pack_unit":"pcs"},
  {"medicinecode":"4123297","medicinename":"Suprimal","pack_quantity":100,"pack_unit":"pcs"},
  {"medicinecode":"4123673","medicinename":"Symmetrel","pack_quantity":200,"pack_unit":"pcs"},
  {"medicinecode":"4123184","medicinename":"Taloxa","pack_quantity":50,"pack_unit":"pcs"},
  {"medicinecode":"4123554","medicinename":"Tapentadol","pack_quantity":100,"pack_unit":"pcs"},
  {"medicinecode":"4123555","medicinename":"Targinact","pack_quantity":200,"pack_unit":"pcs"},
  {"medicinecode":"4123298","medicinename":"Tavegil","pack_quantity":50,"pack_unit":"pcs"},
  {"medicinecode":"4123299","medicinename":"Tavegyl","pack_quantity":100,"pack_unit":"pcs"},
  {"medicinecode":"4123185","medicinename":"Tegretol","pack_quantity":200,"pack_unit":"pcs"},
  {"medicinecode":"4123300","medicinename":"Telfast","pack_quantity":50,"pack_unit":"pcs"},
  {"medicinecode":"4123301","medicinename":"Telfast junior","pack_quantity":100,"pack_unit":"pcs"},
  {"medicinecode":"4123408","medicinename":"Temazepam","pack_quantity":200,"pack_unit":"pcs"},
  {"medicinecode":"4123409","medicinename":"Temesta","pack_quantity":50,"pack_unit":"pcs"},
  {"medicinecode":"4123556","medicinename":"Tepcsesic","pack_quantity":100,"pack_unit":"pcs"},
  {"medicinecode":"4123138","medicinename":"Tentin","pack_quantity":200,"pack_unit":"pcs"},
  {"medicinecode":"4123696","medicinename":"Terbinafine","pack_quantity":50,"pack_unit":"pcs"},
  {"medicinecode":"4123623","medicinename":"Tetmodis","pack_quantity":100,"pack_unit":"pcs"},
  {"medicinecode":"4123624","medicinename":"Tetrabenazine","pack_quantity":200,"pack_unit":"pcs"},
  {"medicinecode":"4123490","medicinename":"Thalidomide","pack_quantity":50,"pack_unit":"pcs"},
  {"medicinecode":"4123625","medicinename":"Tizanidine","pack_quantity":100,"pack_unit":"pcs"},
  {"medicinecode":"4123451","medicinename":"Tolterodine","pack_quantity":200,"pack_unit":"pcs"},
  {"medicinecode":"4123238","medicinename":"Tolvon","pack_quantity":50,"pack_unit":"pcs"},
  {"medicinecode":"4123186","medicinename":"Topamax","pack_quantity":100,"pack_unit":"pcs"},
  {"medicinecode":"4123187","medicinename":"Topiramaat","pack_quantity":200,"pack_unit":"pcs"},
  {"medicinecode":"4123423","medicinename":"Toplexil","pack_quantity":50,"pack_unit":"pcs"},
  {"medicinecode":"4123452","medicinename":"Toviaz","pack_quantity":100,"pack_unit":"pcs"},
  {"medicinecode":"4123239","medicinename":"Tracydal","pack_quantity":200,"pack_unit":"pcs"},
  {"medicinecode":"4123557","medicinename":"Tramadol","pack_quantity":50,"pack_unit":"pcs"},
  {"medicinecode":"4123558","medicinename":"Tramagetic","pack_quantity":1000,"pack_unit":"ml"},
  {"medicinecode":"4123559","medicinename":"Tramal","pack_quantity":200,"pack_unit":"pcs"},
  {"medicinecode":"4123560","medicinename":"Transtec","pack_quantity":50,"pack_unit":"pcs"},
  {"medicinecode":"4123410","medicinename":"Tranxene","pack_quantity":100,"pack_unit":"pcs"},
  {"medicinecode":"4123240","medicinename":"Tranylcypromine","pack_quantity":200,"pack_unit":"pcs"},
  {"medicinecode":"4123241","medicinename":"Trazodon","pack_quantity":50,"pack_unit":"pcs"},
  {"medicinecode":"4123242","medicinename":"Trazolan","pack_quantity":100,"pack_unit":"pcs"},
  {"medicinecode":"4123363","medicinename":"Trevicta","pack_quantity":200,"pack_unit":"pcs"},
  {"medicinecode":"4123674","medicinename":"Trihexyfenidyl","pack_quantity":50,"pack_unit":"pcs"},
  {"medicinecode":"4123188","medicinename":"Trileptal","pack_quantity":100,"pack_unit":"pcs"},
  {"medicinecode":"4123626","medicinename":"Trisporal","pack_quantity":200,"pack_unit":"pcs"},
  {"medicinecode":"4123364","medicinename":"Truxal","pack_quantity":50,"pack_unit":"pcs"},
  {"medicinecode":"4123561","medicinename":"Ultiva","pack_quantity":100,"pack_unit":"pcs"},
  {"medicinecode":"4123453","medicinename":"Urispas","pack_quantity":200,"pack_unit":"pcs"},
  {"medicinecode":"4123627","medicinename":"Utrogestan","pack_quantity":50,"pack_unit":"pcs"},
  {"medicinecode":"4123628","medicinename":"Valdispert","pack_quantity":100,"pack_unit":"pcs"},
  {"medicinecode":"4123243","medicinename":"Valdoxan","pack_quantity":200,"pack_unit":"pcs"},
  {"medicinecode":"4123629","medicinename":"Valeriaan","pack_quantity":50,"pack_unit":"pcs"},
  {"medicinecode":"4123630","medicinename":"Valeriana officinalis","pack_quantity":100,"pack_unit":"pcs"},
  {"medicinecode":"4123411","medicinename":"Valium","pack_quantity":200,"pack_unit":"pcs"},
  {"medicinecode":"4123189","medicinename":"Valproinezuur","pack_quantity":50,"pack_unit":"pcs"},
  {"medicinecode":"4123190","medicinename":"Valproïnezuur zetpillen FNA","pack_quantity":100,"pack_unit":"pcs"},
  {"medicinecode":"4123506","medicinename":"Varenicline","pack_quantity":200,"pack_unit":"pcs"},
  {"medicinecode":"4123491","medicinename":"Velcade","pack_quantity":50,"pack_unit":"pcs"},
  {"medicinecode":"4123244","medicinename":"Venlafaxine","pack_quantity":100,"pack_unit":"pcs"},
  {"medicinecode":"4123492","medicinename":"Verzenios","pack_quantity":200,"pack_unit":"pcs"},
  {"medicinecode":"4123454","medicinename":"Vesicare","pack_quantity":50,"pack_unit":"pcs"},
  {"medicinecode":"4123455","medicinename":"Vesomni","pack_quantity":100,"pack_unit":"pcs"},
  {"medicinecode":"4123191","medicinename":"Vigabatrine","pack_quantity":200,"pack_unit":"pcs"},
  {"medicinecode":"4123192","medicinename":"Vimpat","pack_quantity":50,"pack_unit":"pcs"},
  {"medicinecode":"4123493","medicinename":"Vismodegib","pack_quantity":100,"pack_unit":"pcs"},
  {"medicinecode":"4123697","medicinename":"Voriconazol","pack_quantity":200,"pack_unit":"pcs"},
  {"medicinecode":"4123245","medicinename":"Vortioxetine","pack_quantity":50,"pack_unit":"pcs"},
  {"medicinecode":"4123507","medicinename":"Wellbutrin","pack_quantity":100,"pack_unit":"pcs"},
  {"medicinecode":"4123675","medicinename":"Xadago","pack_quantity":200,"pack_unit":"pcs"},
  {"medicinecode":"4123494","medicinename":"Xalkori","pack_quantity":50,"pack_unit":"pcs"},
  {"medicinecode":"4123412","medicinename":"Xanax","pack_quantity":100,"pack_unit":"pcs"},
  {"medicinecode":"4123631","medicinename":"Xenazine","pack_quantity":200,"pack_unit":"pcs"},
  {"medicinecode":"4123365","medicinename":"Xeplion","pack_quantity":50,"pack_unit":"pcs"},
  {"medicinecode":"4123632","medicinename":"Xerava","pack_quantity":100,"pack_unit":"pcs"},
  {"medicinecode":"4123246","medicinename":"Xeristar","pack_quantity":2000,"pack_unit":"mg"},
  {"medicinecode":"4123302","medicinename":"Xonvea","pack_quantity":50,"pack_unit":"pcs"},
  {"medicinecode":"4123633","medicinename":"Xyrem","pack_quantity":100,"pack_unit":"pcs"},
  {"medicinecode":"4123303","medicinename":"Xyzal","pack_quantity":200,"pack_unit":"pcs"},
  {"medicinecode":"4123304","medicinename":"Zadifen","pack_quantity":50,"pack_unit":"pcs"},
  {"medicinecode":"4123305","medicinename":"Zadifen (oog)","pack_quantity":100,"pack_unit":"pcs"},
  {"medicinecode":"4123366","medicinename":"Zaponex","pack_quantity":200,"pack_unit":"pcs"},
  {"medicinecode":"4123634","medicinename":"Ziconotide","pack_quantity":50,"pack_unit":"pcs"},
  {"medicinecode":"4123440","medicinename":"Zolmitriptan","pack_quantity":100,"pack_unit":"pcs"},
  {"medicinecode":"4123247","medicinename":"Zoloft","pack_quantity":200,"pack_unit":"pcs"},
  {"medicinecode":"4123413","medicinename":"Zolpidem","pack_quantity":50,"pack_unit":"pcs"},
  {"medicinecode":"4123441","medicinename":"Zomig","pack_quantity":100,"pack_unit":"pcs"},
  {"medicinecode":"4123193","medicinename":"Zonegran","pack_quantity":200,"pack_unit":"pcs"},
  {"medicinecode":"4123194","medicinename":"zonisamide","pack_quantity":50,"pack_unit":"pcs"},
  {"medicinecode":"4123414","medicinename":"Zopiclon","pack_quantity":100,"pack_unit":"pcs"},
  {"medicinecode":"4123367","medicinename":"Zuclopentixol","pack_quantity":200,"pack_unit":"pcs"},
  {"medicinecode":"4123508","medicinename":"Zyban","pack_quantity":50,"pack_unit":"pcs"},
  {"medicinecode":"4123495","medicinename":"Zydelig","pack_quantity":100,"pack_unit":"pcs"},
  {"medicinecode":"4123368","medicinename":"Zypadhera","pack_quantity":200,"pack_unit":"pcs"},
  {"medicinecode":"4123369","medicinename":"Zyprexa","pack_quantity":50,"pack_unit":"pcs"},
  {"medicinecode":"4123306","medicinename":"Zyrtec","pack_quantity":1000,"pack_unit":"mg"}
 ]